lab0/part2/alu.v
module alu (
    input [3:0] a,
    input [3:0] b,
    input [2:0] s,
    output reg [3:0] y
);
  // alu has two input operand a and b.
  // It executes different operation over input a and b based on input s
  // then generate result to output y
  // wire [3:0] in_y;
  // wire [3:0] sum;
  // adder4Bit adder (
  //     .x  (a),
  //     .y  (in_y),
  //     .sum(sum)
  // );

  typedef enum logic [2:0] {
    ADD,
    SUB,
    NOT,
    AND,
    OR,
    XOR,
    GT,
    EQL
  } state_t;
  
  // assign in_y = (s[0] == 1'b0)? b: ~b + 1'b1;

  always_comb begin
    case (s)
      ADD: y = a + b;
      SUB: y = a + (~b + 1'b1);
      NOT: y = ~a;
      AND: y = a & b;
      OR:  y = a | b;
      XOR: y = a ^ b;
      GT:  y = a > b ? 4'b0001 : 4'b0000;
      EQL: y = a == b ? 4'b0001 : 4'b0000;
    endcase
  end

endmodule

lab0/waveform.vcd
$version Generated by VerilatedVcd $end
$timescale 1ps $end
 $scope module TOP $end
  $var wire 4 # a [3:0] $end
  $var wire 4 $ b [3:0] $end
  $var wire 3 % s [2:0] $end
  $var wire 4 & y [3:0] $end
  $scope module alu $end
   $var wire 4 # a [3:0] $end
   $var wire 4 $ b [3:0] $end
   $var wire 3 % s [2:0] $end
   $var wire 4 & y [3:0] $end
  $upscope $end
 $upscope $end
$enddefinitions $end


#0
b0100 #
b0010 $
b000 %
b0110 &
#1
b0111 #
b101 %
b0101 &
#2
b1011 #
b1101 $
b111 %
b0000 &
#3
b0110 #
b1000 $
b100 %
b1110 &
#4
b1111 #
b1100 $
b110 %
b0001 &
#5
b0100 #
b0001 $
b100 %
b0101 &
#6
b0010 #
b0011 &
#7
b0110 #
b0000 $
b111 %
b0000 &
#8
b1010 #
b0011 $
b110 %
b0001 &
#9
b0100 #
b001 %
#10
b0110 #
b0111 $
b011 %
b0110 &
#11
b1110 #
b1111 $
b101 %
b0001 &
#12
b0011 #
b1010 $
b010 %
b1100 &
#13
b1011 #
b0000 $
b0100 &
#14
b1111 #
b110 %
b0001 &
#15
b1101 #
b0100 $
b000 %
#16
b1001 #
b0110 $
b001 %
b0011 &
#17
b1110 #
b1101 $
b0001 &
#18
b1101 #
b0111 $
b101 %
b1010 &
#19
b0100 #
b1011 $
b000 %
b1111 &
#20
b0101 #
b0010 $
b111 %
b0000 &
#21
b1000 #
b0000 $
b110 %
b0001 &
#22
b1101 #
b0100 $
b001 %
b1001 &
#23
b1111 #
b1111 $
b0000 &
#24
b1001 #
b1110 $
b1011 &
#25
b1111 #
b1011 $
b110 %
b0001 &
#26
b0111 #
b0100 $
b100 %
b0111 &
#27
b0001 #
b0010 $
b001 %
b1111 &
#28
b1010 #
b0000 $
b1010 &
#29
b0111 #
b0100 $
b100 %
b0111 &
#30
b1001 $
b110 %
b0000 &
#31
b1111 #
b0001 $
b111 %
#32
b0101 #
b1110 $
b011 %
b0100 &
#33
b0110 #
b1101 $
b010 %
b1001 &
#34
b1000 #
b0110 $
b000 %
b1110 &
#35
b1001 #
b0101 $
b011 %
b0001 &
#36
b1111 #
b1101 $
b111 %
b0000 &
#37
b1100 #
b1110 $
b010 %
b0011 &
#38
b0101 #
b1000 $
b1010 &
#39
b0110 #
b0000 $
b110 %
b0001 &
#40
b0011 #
b0111 $
b111 %
b0000 &
#41
b0001 #
b0110 $
b000 %
b0111 &
#42
b0000 #
b1100 $
b110 %
b0000 &
#43
b0011 #
b0010 $
b011 %
b0010 &
#44
b0101 #
b1010 $
b001 %
b1011 &
#45
b0100 $
b110 %
b0001 &
#46
b0000 #
b0011 $
b011 %
b0000 &
#47
b1111 $
b001 %
b0001 &
#48
b0010 #
b0101 $
b010 %
b1101 &
#49
b0100 #
b1011 $
b1011 &
#50
b1010 #
b1110 $
b001 %
b1100 &
#51
b1001 #
b0000 $
b000 %
b1001 &
#52
b100 %
#53
b0111 #
b0100 $
b110 %
b0001 &
#54
b0010 #
b1001 $
b001 %
b1001 &
#55
b0011 #
b1111 $
b101 %
b1100 &
#56
b1001 #
b000 %
b1000 &
#57
b1101 #
b1100 &
#58
b1110 #
b0001 $
b101 %
b1111 &
#59
b1000 #
b0101 $
b000 %
b1101 &
#60
b0010 #
b1111 $
b111 %
b0000 &
#61
b0100 #
b1000 $
#62
b1100 #
b0001 $
#63
b0000 #
b1000 $
b011 %
#64
b0110 #
b1010 $
b101 %
b1100 &
#65
b0111 #
b1101 $
b100 %
b1111 &
#66
b1100 #
b0111 $
b011 %
b0100 &
#67
b0101 #
b0100 $
#68
b1101 #
b0010 $
b100 %
b1111 &
#69
b1010 #
b1011 $
b010 %
b0101 &
#70
b0010 #
b1101 $
b001 %
#71
b1001 #
b0001 $
b010 %
b0110 &
#72
b0000 #
b1101 $
b011 %
b0000 &
#73
b1000 #
b100 %
b1101 &
#74
b0011 #
b0100 $
b110 %
b0000 &
#75
b1000 #
b1011 $
b100 %
b1011 &
#76
b1100 #
b1000 $
b011 %
b1000 &
#77
b0000 #
b1101 $
b111 %
b0000 &
#78
b0011 #
b1010 $
b001 %
b1001 &
#79
b0111 #
b0100 $
b100 %
b0111 &
#80
b0001 #
b0110 $
b010 %
b1110 &
#81
b1011 #
b0000 $
b011 %
b0000 &
#82
b1101 #
b001 %
b1101 &
#83
b0000 #
b1000 $
b110 %
b0000 &
#84
b1100 #
b1100 $
b010 %
b0011 &
#85
b0011 #
b0100 $
b110 %
b0000 &
#86
b0111 #
b0001 $
b0001 &
#87
b0010 #
b011 %
b0000 &
#88
b0001 #
b0100 $
b101 %
b0101 &
#89
b0010 #
b1011 $
b001 %
b0111 &
#90
b1111 #
b1101 $
b111 %
b0000 &
#91
b1001 #
b1000 $
#92
b0100 #
b0101 $
b000 %
b1001 &
#93
b1101 #
b0010 &
#94
b0100 #
b0010 $
b100 %
b0110 &
#95
b1110 #
b0101 $
b001 %
b1001 &
#96
b0100 #
b1100 $
b010 %
b1011 &
#97
b0010 #
b1110 $
b011 %
b0010 &
#98
b1101 #
b1111 $
b111 %
b0000 &
#99
b0010 #
b0001 $
b010 %
b1101 &
#100
b1011 #
b0000 $
b111 %
b0000 &
#101
b1001 $
#102
b1010 #
b1110 $
b100 %
b1110 &
#103
b1011 $
b010 %
b0101 &
#104
b0011 #
b1111 $
b100 %
b1111 &
#105
b0111 #
b1110 $
b001 %
b1001 &
#106
b0000 #
b0010 $
b101 %
b0010 &
#107
b1010 #
b0101 $
b011 %
b0000 &
#108
b0101 #
b0010 $
b010 %
b1010 &
#109
b0100 #
b0101 $
b011 %
b0100 &
#110
b1111 #
b0000 $
b100 %
b1111 &
#111
b0110 #
b1011 $
b101 %
b1101 &
#112
b0110 $
b011 %
b0110 &
#113
b1010 #
b0000 $
b111 %
b0000 &
#114
b0100 #
b0011 $
b110 %
b0001 &
#115
b0000 #
b1011 $
b100 %
b1011 &
#116
b0001 #
b111 %
b0000 &
#117
b1110 #
b0110 $
b100 %
b1110 &
#118
b1001 #
b1011 $
b110 %
b0000 &
#119
b0011 #
b0000 $
b011 %
#120
b1111 #
b1111 $
b100 %
b1111 &
#121
b1011 #
b0101 $
b111 %
b0000 &
#122
b0000 #
b1011 $
b101 %
b1011 &
#123
b0100 #
b0110 $
b110 %
b0000 &
#124
b0011 #
b1010 $
b001 %
b1001 &
#125
b0001 #
b1011 $
b100 %
b1011 &
#126
b1110 #
b1100 $
b000 %
b1010 &
#127
b1101 #
b1011 $
b110 %
b0001 &
#128
b0001 #
b0100 $
b001 %
b1101 &
#129
b0111 #
b1000 $
b1111 &
#130
b0011 #
b0111 $
b000 %
b1010 &
#131
b1111 #
b0010 $
b110 %
b0001 &
#132
b0110 #
b001 %
b0100 &
#133
b0100 #
b0110 $
b111 %
b0000 &
#134
b0010 #
b1001 $
b010 %
b1101 &
#135
b0011 #
b1011 $
b101 %
b1000 &
#136
b0000 #
b1001 $
b001 %
b0111 &
#137
b1000 #
b0110 $
b100 %
b1110 &
#138
b0110 #
b0111 $
b001 %
b1111 &
#139
b1111 #
b1110 $
b0001 &
#140
b1001 #
b0001 $
b000 %
b1010 &
#141
b0001 #
b0000 $
b010 %
b1110 &
#142
b1111 #
b0111 $
b100 %
b1111 &
#143
b1001 #
b1011 $
b011 %
b1001 &
#144
b1000 #
b1101 $
b100 %
b1101 &
#145
b0010 #
b0000 $
b111 %
b0000 &
#146
b0111 #
b000 %
b0111 &
#147
b1001 #
b1000 $
b110 %
b0001 &
#148
b0101 #
b1110 $
b101 %
b1011 &
#149
b0110 #
b100 %
b1110 &
#150
b1111 #
b0111 $
b101 %
b1000 &
#151
b1000 $
b110 %
b0001 &
#152
b0001 #
b101 %
b1001 &
#153
b0110 #
b0001 $
b000 %
b0111 &
#154
b0001 #
b1001 $
b101 %
b1000 &
#155
b0101 #
b1100 $
b1001 &
#156
b0011 $
b110 %
b0001 &
#157
b1101 #
b1100 $
#158
b1100 #
b0010 $
b101 %
b1110 &
#159
b0001 #
b1000 $
b011 %
b0000 &
#160
b0101 #
b010 %
b1010 &
#161
b1011 #
b0111 $
b0100 &
#162
b0001 #
b1001 $
b1110 &
#163
b1110 #
b1111 $
b011 %
#164
b0110 #
b0000 $
b101 %
b0110 &
#165
b1011 #
b0101 $
b001 %
#166
b0000 #
b1010 $
b100 %
b1010 &
#167
b0110 #
b1000 $
b001 %
b1110 &
#168
b0101 #
b0100 $
b011 %
b0100 &
#169
b0010 #
b0101 $
b0000 &
#170
b1101 #
b1011 $
b1001 &
#171
b1111 #
b0110 $
b0110 &
#172
b1001 #
b0111 $
b100 %
b1111 &
#173
b1100 #
b0101 $
b011 %
b0100 &
#174
b1111 #
b1011 $
b1011 &
#175
b1100 #
b0110 $
b000 %
b0010 &
#176
b0101 #
b011 %
b0100 &
#177
b0010 #
b1101 $
b0000 &
#178
b1011 #
b0010 $
b111 %
#179
b0110 #
b0100 $
b100 %
b0110 &
#180
b1001 #
b0001 $
b111 %
b0000 &
#181
b0101 #
b0000 $
b101 %
b0101 &
#182
b1000 #
b1001 $
b100 %
b1001 &
#183
b0100 #
b0101 $
b001 %
b1111 &
#184
b1111 #
b100 %
#185
b1010 #
b0001 $
b010 %
b0101 &
#186
b0111 $
b001 %
b0011 &
#187
b0101 #
b1001 $
b110 %
b0000 &
#188
b1000 #
b0100 $
b000 %
b1100 &
#189
b1111 #
b1010 $
b100 %
b1111 &
#190
b1100 #
b0011 $
b101 %
#191
b0011 #
b1000 $
b1011 &
#192
b0001 #
b0000 $
b110 %
b0001 &
#193
b0101 #
b0100 $
b100 %
b0101 &
#194
b1111 #
b0011 $
b001 %
b1100 &
#195
b0011 #
b1101 $
b010 %
#196
b1110 #
b1000 $
b001 %
b0110 &
#197
b1111 #
b1101 $
b010 %
b0000 &
#198
b1101 #
b0110 $
b110 %
b0001 &
#199
b0101 $
b000 %
b0010 &
#200
b0001 #
b0001 $
b100 %
b0001 &
#201
b0110 #
b0101 $
b0111 &
#202
b1011 #
b0110 $
b101 %
b1101 &
#203
b1001 #
b1011 $
b001 %
b1110 &
#204
b1101 #
b1010 $
b101 %
b0111 &
#205
b0110 #
b1110 $
b010 %
b1001 &
#206
b0001 #
b1100 $
b1110 &
#207
b0010 #
b1011 $
b000 %
b1101 &
#208
b1101 #
b1000 $
b110 %
b0001 &
#209
b1011 #
b0101 $
b011 %
#210
b0100 #
b0110 $
b101 %
b0010 &
#211
b0000 #
b1100 $
b010 %
b1111 &
#212
b0100 #
b0111 $
b000 %
b1011 &
#213
b1001 #
b0000 $
b011 %
b0000 &
#214
b0011 #
b1110 $
b110 %
#215
b0000 #
b0100 $
b100 %
b0100 &
#216
b1010 #
b0101 $
b000 %
b1111 &
#217
b1101 #
b1000 $
b011 %
b1000 &
#218
b0101 $
b0101 &
#219
b0011 #
b0000 $
b000 %
b0011 &
#220
b1110 #
b0100 $
b110 %
b0001 &
#221
b1011 #
b010 %
b0100 &
#222
b1101 #
b1001 $
b001 %
#223
b0101 #
b0010 $
b0011 &
#224
b1001 #
b0101 $
b111 %
b0000 &
#225
b0111 #
b100 %
b0111 &
#226
b0011 #
b0000 $
b001 %
b0011 &
#227
b1011 #
b1101 $
b1110 &
#228
b1110 #
b1010 $
b110 %
b0001 &
#229
b1001 #
b1101 $
b111 %
b0000 &
#230
b1011 $
b011 %
b1001 &
#231
b1111 #
b0111 $
b000 %
b0110 &
#232
b0001 #
b0100 $
b001 %
b1101 &
#233
b1010 #
b1010 $
b011 %
b1010 &
#234
b0011 #
b0011 $
b001 %
b0000 &
#235
b1011 #
b1010 $
b110 %
b0001 &
#236
b0111 #
b1101 $
b0000 &
#237
b1000 #
b1000 $
b011 %
b1000 &
#238
b0010 #
b0110 $
b101 %
b0100 &
#239
b0000 #
b1111 $
b010 %
b1111 &
#240
b1111 #
b1000 $
b110 %
b0001 &
#241
b0011 #
b0111 $
b101 %
b0100 &
#242
b1011 #
b1000 $
b001 %
b0011 &
#243
b1100 #
b0010 $
b011 %
b0000 &
#244
b1111 #
b0101 $
b110 %
b0001 &
#245
b1000 #
b0000 $
b000 %
b1000 &
#246
b0111 #
b0111 $
b101 %
b0000 &
#247
b0101 #
b0000 $
b0101 &
#248
b0001 #
b0010 $
b011 %
b0000 &
#249
b0110 #
b010 %
b1001 &
#250
b1001 #
b0110 &
#251
b0111 #
b0101 $
b001 %
b0010 &
#252
b1100 #
b0000 $
b1100 &
#253
b0101 #
b1100 $
b011 %
b0100 &
#254
b1001 #
b1011 $
b001 %
b1110 &
#255
b1111 #
b0100 $
b1011 &
#256
b0000 #
b1011 $
b0101 &
#257
b1101 #
b0000 $
b1101 &
#258
b0011 #
b0001 $
b011 %
b0001 &
#259
b1110 #
b1000 $
b101 %
b0110 &
#260
b1001 #
b0001 $
b111 %
b0000 &
#261
b1011 #
b1000 $
b100 %
b1011 &
#262
b0101 #
b0100 $
b0101 &
#263
b0110 #
b1001 $
b000 %
b1111 &
#264
b1010 #
b0010 $
b100 %
b1010 &
#265
b0011 #
b000 %
b0101 &
#266
b1100 #
b011 %
b0000 &
#267
b1101 #
b1111 $
b1101 &
#268
b1110 #
b0010 $
b101 %
b1100 &
#269
b0001 #
b0001 $
b0000 &
#270
b0111 #
b1010 $
b110 %
#271
b1110 #
b0101 $
b0001 &
#272
b1011 #
b1010 $
b010 %
b0100 &
#273
b0111 #
b0001 $
b011 %
b0001 &
#274
b0000 #
b1011 $
b110 %
b0000 &
#275
b0100 #
b1110 $
b000 %
b0010 &
#276
b1100 #
b1010 $
b010 %
b0011 &
#277
b1111 #
b1000 $
b001 %
b0111 &
#278
b0010 #
b0110 $
b100 %
b0110 &
#279
b0111 #
b1000 $
b101 %
b1111 &
#280
b0100 #
b1111 $
b111 %
b0000 &
#281
b0010 #
b1101 $
b100 %
b1111 &
#282
b1000 #
b1000 $
b111 %
b0001 &
#283
b0010 #
b0000 $
b000 %
b0010 &
#284
b0110 #
b011 %
b0000 &
#285
b1100 #
b0100 $
b001 %
b1000 &
#286
b0100 #
b0000 $
b011 %
b0000 &
#287
b1110 #
b1111 $
b1110 &
#288
b0111 #
b0001 $
b010 %
b1000 &
#289
b0011 #
b1001 $
b1100 &
#290
b0000 #
b1101 $
b001 %
b0011 &
#291
b0111 #
b0000 $
b110 %
b0001 &
#292
b0100 #
b1000 $
b111 %
b0000 &
#293
b1011 #
b1011 $
b0001 &
#294
b0011 #
b0001 $
b0000 &
#295
b0110 #
b1101 $
b011 %
b0100 &
#296
b0111 #
b0001 $
b0001 &
#297
b0010 #
b1111 $
b010 %
b1101 &
#298
b0110 #
b0110 $
b011 %
b0110 &
#299
b0000 #
b1010 $
b100 %
b1010 &
#300
b0010 #
b010 %
b1101 &
#301
b0011 #
b0010 $
b1100 &
#302
b0001 #
b0110 $
b1110 &
#303
b1000 #
b0001 $
b101 %
b1001 &
#304
b1111 #
b0100 $
b110 %
b0001 &
#305
b0110 #
b1010 $
b011 %
b0010 &
#306
b0001 #
b0001 $
b100 %
b0001 &
#307
b1100 #
b0011 $
b011 %
b0000 &
#308
b0110 #
b1001 $
b010 %
b1001 &
#309
b0010 #
b100 %
b1011 &
#310
b0110 #
b1011 $
b110 %
b0000 &
#311
b1000 #
b1110 $
b000 %
b0110 &
#312
b1010 #
b0000 $
b110 %
b0001 &
#313
b0101 #
b1000 $
b111 %
b0000 &
#314
b1010 #
b011 %
b1000 &
#315
b0001 #
b1110 $
b101 %
b1111 &
#316
b0100 #
b0000 $
b110 %
b0001 &
#317
b1001 #
b1100 $
b010 %
b0110 &
#318
b1100 #
b0011 $
b011 %
b0000 &
#319
b0110 #
b0101 $
b101 %
b0011 &
#320
b1010 #
b1011 $
b000 %
b0101 &
#321
b1001 #
b0100 $
b111 %
b0000 &
#322
b1110 $
#323
b0000 #
b0011 $
#324
b0111 #
b1110 $
#325
b0011 #
b1111 $
b110 %
#326
b1000 #
b0011 $
b0001 &
#327
b1111 #
b1100 $
b010 %
b0000 &
#328
b1001 #
b1001 $
b101 %
#329
b1100 #
b1111 $
b010 %
b0011 &
#330
b1001 #
b1010 $
b110 %
b0000 &
#331
b0010 #
b0011 $
b010 %
b1101 &
#332
b1001 #
b1100 $
b000 %
b0101 &
#333
b0000 #
b100 %
b1100 &
#334
b1111 #
b0100 $
b010 %
b0000 &
#335
b0111 #
b0111 $
b001 %
#336
b1101 #
b1111 $
b100 %
b1111 &
#337
b0011 #
b1110 $
b001 %
b0101 &
#338
b0101 #
b0111 $
b010 %
b1010 &
#339
b1011 #
b0100 $
b001 %
b0111 &
#340
b0101 #
b1101 $
b011 %
b0101 &
#341
b1011 #
b1111 $
b110 %
b0000 &
#342
b0101 #
b1000 $
b011 %
#343
b1110 #
b111 %
#344
b1010 #
b011 %
b1000 &
#345
b0100 #
b1111 $
b010 %
b1011 &
#346
b1101 #
b1100 $
b0010 &
#347
b1001 #
b1111 $
b000 %
b1000 &
#348
b0010 #
b0100 $
b0110 &
#349
b0100 #
b1111 $
b100 %
b1111 &
#350
b0110 #
b0101 $
b001 %
b0001 &
#351
b0001 #
b0000 $
#352
b0000 #
b0110 $
b1010 &
#353
b1011 #
b0100 $
b010 %
b0100 &
#354
b0010 #
b1110 $
b1101 &
#355
b1110 #
b0010 $
b001 %
b1100 &
#356
b0000 #
b1111 $
b101 %
b1111 &
#357
b0010 #
b1000 $
b100 %
b1010 &
#358
b0011 #
b1011 $
b000 %
b1110 &
#359
b1011 #
b1111 $
b1010 &
#360
b0111 #
b0101 $
b101 %
b0010 &
#361
b0000 #
b0111 $
b0111 &
#362
b1001 #
b011 %
b0001 &
#363
b1011 #
b0010 $
b111 %
b0000 &
#364
b0101 #
b0100 $
b101 %
b0001 &
#365
b0111 #
b0010 $
b111 %
b0000 &
#366
b1000 #
b0011 $
b110 %
b0001 &
#367
b0101 #
b0101 $
b111 %
#368
b0001 #
b1000 $
b010 %
b1110 &
#369
b0011 $
b001 %
#370
b1010 $
b111 %
b0000 &
#371
b0110 #
b1011 $
b110 %
#372
b1100 #
b0100 $
b101 %
b1000 &
#373
b0111 #
b1111 $
b111 %
b0000 &
#374
b0100 $
b011 %
b0100 &
#375
b0100 #
b1011 $
b110 %
b0000 &
#376
b0011 $
b001 %
b0001 &
#377
b0010 #
b1000 $
b110 %
b0000 &
#378
b1001 #
b1001 $
b111 %
b0001 &
#379
b1011 #
b1011 $
b010 %
b0100 &
#380
b1101 #
b1100 $
b101 %
b0001 &
#381
b0100 #
b0011 $
b000 %
b0111 &
#382
b0010 #
b1111 $
b100 %
b1111 &
#383
b0111 #
b0110 $
b0111 &
#384
b1110 #
b1101 $
b000 %
b1011 &
#385
b1001 #
b0010 $
b100 %
#386
b0111 #
b0110 $
b111 %
b0000 &
#387
b1000 #
b1000 $
b000 %
#388
b1111 #
b0010 $
b001 %
b1101 &
#389
b1110 #
b1101 $
b100 %
b1111 &
#390
b0000 #
b1010 $
b001 %
b0110 &
#391
b1101 #
b1110 $
b100 %
b1111 &
#392
b0101 #
b0000 $
b011 %
b0000 &
#393
b0010 #
b0111 $
b001 %
b1011 &
#394
b1110 #
b0101 $
b111 %
b0000 &
#395
b1111 $
b001 %
b1111 &
#396
b1010 #
b0110 $
b111 %
b0000 &
#397
b1111 $
#398
b0010 #
b1110 $
b001 %
b0100 &
#399
b0011 #
b1100 $
b111 %
b0000 &
#400
b0000 #
b001 %
b0100 &
#401
b1001 #
b1010 $
b000 %
b0011 &
#402
b0101 #
b1111 $
b0100 &
#403
b0000 #
b0001 $
b0001 &
#404
b0001 #
b1111 $
b101 %
b1110 &
#405
b0000 #
b1110 $
b100 %
#406
b0001 #
b1000 $
b011 %
b0000 &
#407
b1000 #
b0010 $
b010 %
b0111 &
#408
b0100 $
b000 %
b1100 &
#409
b1001 #
b1000 $
b100 %
b1001 &
#410
b1000 #
b000 %
b0000 &
#411
b0010 #
b0001 $
b010 %
b1101 &
#412
b1010 #
b0110 $
b0101 &
#413
b0010 #
b011 %
b0010 &
#414
b0111 $
#415
b1000 #
b1000 $
b001 %
b0000 &
#416
b1100 #
b1001 $
b0011 &
#417
b0111 #
b0010 $
b100 %
b0111 &
#418
b0001 #
b1010 $
b000 %
b1011 &
#419
b1001 #
b0011 $
b1100 &
#420
b1101 #
b1100 $
b1001 &
#421
b1110 #
b1110 $
b001 %
b0000 &
#422
b1000 #
b1000 $
b111 %
b0001 &
#423
b0010 #
b1010 $
b101 %
b1000 &
#424
b1110 #
b1101 $
b0011 &
#425
b1001 #
b0101 $
b1100 &
#426
b0010 #
b0001 $
b110 %
b0001 &
#427
b0011 #
b1001 $
b000 %
b1100 &
#428
b0111 #
b1010 $
b010 %
b1000 &
#429
b0000 #
b0100 $
b110 %
b0000 &
#430
b0001 $
b010 %
b1111 &
#431
b1001 #
b1111 $
b000 %
b1000 &
#432
b0010 #
b1000 $
b1010 &
#433
b1010 $
b010 %
b1101 &
#434
b0111 #
b1000 $
b111 %
b0000 &
#435
b0100 #
b0001 $
b100 %
b0101 &
#436
b1001 #
b0011 $
b110 %
b0001 &
#437
b1000 #
b0111 $
b111 %
b0000 &
#438
b1110 $
b001 %
b1010 &
#439
b0011 #
b101 %
b1101 &
#440
b0001 #
b1111 $
b111 %
b0000 &
#441
b1011 #
b1000 $
b110 %
b0001 &
#442
b0011 #
b1010 $
b0000 &
#443
b1100 $
b001 %
b0111 &
#444
b1101 #
b0100 $
b1001 &
#445
b0101 #
b1000 $
b011 %
b0000 &
#446
b0001 #
b0010 $
b110 %
#447
b1111 #
b1010 $
b101 %
b0101 &
#448
b0110 #
b0010 $
b100 %
b0110 &
#449
b1000 #
b0101 $
b010 %
b0111 &
#450
b1101 #
b0110 $
b001 %
#451
b0100 #
b0001 $
b0011 &
#452
b1011 #
b0100 $
b100 %
b1111 &
#453
b1001 #
b0111 $
b000 %
b0000 &
#454
b0010 #
b0101 $
b100 %
b0111 &
#455
b0100 #
b1010 $
b101 %
b1110 &
#456
b0111 #
b1011 $
b111 %
b0000 &
#457
b1101 #
b001 %
b0010 &
#458
b1011 #
b0001 $
b011 %
b0001 &
#459
b0111 #
b1001 $
b001 %
b1110 &
#460
b0001 #
b0111 $
b111 %
b0000 &
#461
b1011 #
b1011 $
b001 %
#462
b1100 #
b0110 $
b101 %
b1010 &
#463
b1000 #
b0000 $
b1000 &
#464
b0001 #
b0010 $
b010 %
b1110 &
#465
b1101 #
b0110 $
b100 %
b1111 &
#466
b0010 #
b1101 $
b111 %
b0000 &
#467
b1001 #
b1011 $
b010 %
b0110 &
#468
b1010 #
b0110 $
b100 %
b1110 &
#469
b1110 #
b1101 $
b101 %
b0011 &
#470
b0111 #
b1110 $
b100 %
b1111 &
#471
b0110 #
b1001 $
b000 %
#472
b0111 #
b0110 $
b110 %
b0001 &
#473
b1101 #
b1110 $
b0000 &
#474
b1010 #
b1111 $
b001 %
b1011 &
#475
b1100 #
b1101 $
b111 %
b0000 &
#476
b1000 #
b1111 $
b101 %
b0111 &
#477
b1111 #
b1001 $
b000 %
b1000 &
#478
b0010 #
b0011 $
b110 %
b0000 &
#479
b0110 #
b0001 $
b011 %
#480
b0011 #
b1000 $
b001 %
b1011 &
#481
b1000 #
b1111 $
b011 %
b1000 &
#482
b0110 $
b001 %
b0010 &
#483
b1110 #
b0011 $
b111 %
b0000 &
#484
b0101 #
b1101 $
#485
b1110 #
b1001 $
b100 %
b1111 &
#486
b1101 #
b0001 $
b011 %
b0001 &
#487
b1010 #
b100 %
b1011 &
#488
b0010 #
b0011 $
b000 %
b0101 &
#489
b0000 #
b1001 $
b001 %
b0111 &
#490
b1011 #
b1100 $
b010 %
b0100 &
#491
b0101 #
b0100 $
b001 %
b0001 &
#492
b1000 #
b1100 $
b111 %
b0000 &
#493
b0001 #
b1011 $
b011 %
b0001 &
#494
b1000 #
b0000 $
b000 %
b1000 &
#495
b1111 #
b1110 $
b010 %
b0000 &
#496
b0011 #
b1011 $
b011 %
b0011 &
#497
b0111 #
b0110 $
b100 %
b0111 &
#498
b0011 #
b1000 $
b111 %
b0000 &
#499
b1001 $
b000 %
b1100 &
#500
b0101 #
b0100 $
b101 %
b0001 &
#501
b1111 #
b1001 $
b001 %
b0110 &
#502
b1000 #
b0001 $
b110 %
b0001 &
#503
b0111 #
b0010 $
b001 %
b0101 &
#504
b1010 #
b1011 $
b1111 &
#505
b1011 #
b1010 $
b111 %
b0000 &
#506
b0101 #
b1110 $
b010 %
b1010 &
#507
b0000 #
b0101 $
b000 %
b0101 &
#508
b1101 #
b1000 $
b001 %
#509
b1100 #
b1100 $
b010 %
b0011 &
#510
b0101 #
b0001 $
b110 %
b0001 &
#511
b1010 #
b0000 $
b000 %
b1010 &
#512
b0011 #
b1000 $
b001 %
b1011 &
#513
b1001 #
b1111 $
b100 %
b1111 &
#514
b1010 #
b1010 $
b111 %
b0001 &
#515
b1011 #
b0101 $
b001 %
b0110 &
#516
b1010 #
b1010 $
b111 %
b0001 &
#517
b0101 #
b100 %
b1111 &
#518
b0111 $
b101 %
b0010 &
#519
b1110 #
b0100 $
b001 %
b1010 &
#520
b0000 #
b1001 $
b010 %
b1111 &
#521
b0111 #
b0011 $
b1000 &
#522
b0110 $
#523
b1000 #
b0000 $
b001 %
#524
b1100 #
b1010 $
b011 %
#525
b1011 #
b0110 $
b000 %
b0001 &
#526
b0101 #
b0000 $
b010 %
b1010 &
#527
b1100 #
b0101 $
b101 %
b1001 &
#528
b1001 #
b1011 $
b100 %
b1011 &
#529
b1110 #
b1001 $
b000 %
b0111 &
#530
b1111 #
b1010 $
b001 %
b0101 &
#531
b0001 #
b0001 $
b100 %
b0001 &
#532
b0011 #
b1000 $
b011 %
b0000 &
#533
b1101 #
b0000 $
#534
b0110 #
b1101 $
b101 %
b1011 &
#535
b1010 #
b1000 $
b011 %
b1000 &
#536
b0010 #
b1101 $
b100 %
b1111 &
#537
b0101 #
b1010 $
b001 %
b1011 &
#538
b0010 #
b0011 $
b100 %
b0011 &
#539
b0110 #
b0001 $
b110 %
b0001 &
#540
b1111 #
b0000 $
b000 %
b1111 &
#541
b0000 #
b0001 $
b001 %
#542
b0101 #
b0100 $
b0001 &
#543
b0000 #
b0001 $
b1111 &
#544
b1011 #
b0111 $
b110 %
b0001 &
#545
b0000 #
b0001 $
b111 %
b0000 &
#546
b1100 #
b0100 $
b100 %
b1100 &
#547
b1000 #
b1001 $
b110 %
b0000 &
#548
b1001 #
b1011 $
b001 %
b1110 &
#549
b0110 #
b0001 $
b010 %
b1001 &
#550
b1100 #
b0000 $
b0011 &
#551
b0001 $
b011 %
b0000 &
#552
b1101 #
b0110 $
b111 %
#553
b0110 #
b000 %
b1100 &
#554
b1111 #
b0001 $
b0000 &
#555
b0110 #
b001 %
b0101 &
#556
b0101 #
b1101 $
b101 %
b1000 &
#557
b0001 #
b0101 $
b110 %
b0000 &
#558
b1000 #
b1111 $
b001 %
b1001 &
#559
b0001 #
b0101 $
b011 %
b0001 &
#560
b1100 #
b0001 $
b0000 &
#561
b0110 #
b1101 $
b100 %
b1111 &
#562
b0010 #
b1010 $
b010 %
b1101 &
#563
b0001 #
b0000 $
b000 %
b0001 &
#564
b0010 #
b1111 $
b001 %
b0011 &
#565
b1010 #
b0101 $
b011 %
b0000 &
#566
b0011 #
b1010 $
b000 %
b1101 &
#567
b0001 #
b1100 $
b110 %
b0000 &
#568
b0111 #
b0100 $
b101 %
b0011 &
#569
b1001 #
b0101 $
b010 %
b0110 &
#570
b1100 #
b0001 $
b011 %
b0000 &
#571
b1111 #
b1000 $
b000 %
b0111 &
#572
b0100 #
b1010 $
b010 %
b1011 &
#573
b1110 #
b1011 $
b0001 &
#574
b1111 #
b1101 $
b001 %
b0010 &
#575
b0000 #
b0111 $
b111 %
b0000 &
#576
b0011 #
b1011 $
b001 %
b1000 &
#577
b0100 #
b1100 $
b101 %
#578
b1010 #
b0011 $
b001 %
b0111 &
#579
b1111 #
b1100 $
b111 %
b0000 &
#580
b1001 #
b1000 $
b000 %
b0001 &
#581
b0100 #
b1100 &
#582
b1100 #
b1100 $
b010 %
b0011 &
#583
b1110 #
b1010 $
b110 %
b0001 &
#584
b0000 #
b1001 $
b011 %
b0000 &
#585
b0001 #
b1010 $
#586
b1000 #
b1101 $
b110 %
#587
b1010 #
b0001 $
b010 %
b0101 &
#588
b0111 #
b1011 $
b101 %
b1100 &
#589
b1001 #
b1010 $
b010 %
b0110 &
#590
b0000 #
b0011 $
b1111 &
#591
b1000 #
b0111 $
b0111 &
#592
b1001 #
b0011 $
b110 %
b0001 &
#593
b0011 #
b0001 $
b001 %
b0010 &
#594
b1001 #
b010 %
b0110 &
#595
b1101 #
b0011 $
b100 %
b1111 &
#596
b1000 #
b1011 $
b010 %
b0111 &
#597
b1110 #
b0101 $
b011 %
b0100 &
#598
b0000 #
b1101 $
b111 %
b0000 &
